logkk/__init__.py
logkk/errors.py
logkk/handlers.py
logkk/level.py
logkk/logger.py
logkk/manager.py
logkk-0.7.0.dist-info/METADATA
logkk-0.7.0.dist-info/WHEEL
logkk-0.7.0.dist-info/top_level.txt
logkk-0.7.0.dist-info/RECORD
