Metadata-Version: 2.1
Name: logkk
Version: 0.7.0
Summary: 日志组件
Home-page: https://github.com/olivetree/logkk
Author: olivetree
Author-email: olivetree123@163.com
Classifier: Programming Language :: Python :: 3
Classifier: License :: OSI Approved :: MIT License
Classifier: Operating System :: OS Independent
Requires-Python: >=3.7
